pymv/__init__.py
pymv/main.py
pymv/test.py
pymv-1.4.dist-info/METADATA
pymv-1.4.dist-info/WHEEL
pymv-1.4.dist-info/entry_points.txt
pymv-1.4.dist-info/top_level.txt
pymv-1.4.dist-info/RECORD
