Metadata-Version: 2.1
Name: pymv
Version: 1.4
Summary: CLI wrapper of rope's module moving functionality
Home-page: https://github.com/Ridecell/pymv
Author: Ridecell & contributors
Author-email: john@johngm.com
License: MIT
Platform: UNKNOWN
Requires-Python: >=3.7.0
